{"deviceId": {"0": "dde4ca", "1": "ace9d7", "2": "c1b193", "3": "c38754", "4": "c542cb", "5": "ddec9f", "6": "ddec9c", "7": "e9bb33", "8": "97b3ef", "9": "c3caf2"}, "deviceName": {"0": "South Laser", "1": "3PH Collector", "2": "Waterjet", "3": "Drill Press", "4": "Tablesaw", "5": "Bench Grinder", "6": "Planer", "7": "Jointer", "8": "Miter Saw", "9": "Belt/Disc Sander"}, "deviceType": {"0": "trigger", "1": "collector", "2": "trigger", "3": "trigger", "4": "trigger", "5": "trigger", "6": "trigger", "7": "trigger", "8": "trigger", "9": "trigger"}, "value": {"0": 12736, "1": 2490, "2": 1496, "3": 685, "4": 466, "5": 276, "6": 191, "7": 132, "8": 49, "9": 8}}